grf/__init__.py
grf/actions.py
grf/cache.py
grf/colour.py
grf/common.py
grf/constants.py
grf/decompile.py
grf/dev.py
grf/exceptions.py
grf/grf.py
grf/image.py
grf/parser.py
grf/parsetab.py
grf/sprites.py
grf/strings.py
grf/utils.py
grf/va2vars.py
grf/vox.py
grf/lib/__init__.py
grf/lib/callback.py
grf/lib/industry.py
grf/lib/misc.py
grf/lib/object.py
grf/lib/rv.py
grf/lib/ship.py
grf/lib/train.py
grf/lib/vehicle.py
grf-0.3.1.dist-info/LICENSE
grf-0.3.1.dist-info/METADATA
grf-0.3.1.dist-info/WHEEL
grf-0.3.1.dist-info/entry_points.txt
grf-0.3.1.dist-info/top_level.txt
grf-0.3.1.dist-info/RECORD
