Metadata-Version: 2.1
Name: grf
Version: 0.3.1
Summary: Framework for making OpenTTD NewGRF files
Home-page: UNKNOWN
Author: dP
License: UNKNOWN
Platform: UNKNOWN
Requires-Python: >=3.6.9
License-File: LICENSE
Requires-Dist: nml ==0.7.5
Requires-Dist: numpy ==1.25.0
Requires-Dist: Pillow ==9.4.0
Requires-Dist: ply ==3.11
Requires-Dist: typeguard ==4.1.5
